CHANGES.txt
CONTRIBUTORS.txt
README.txt
bootstrap.py
buildout.cfg
setup.py
docs/LICENSE.GPL
docs/LICENSE.txt
src/collective/__init__.py
src/collective.customlogin.egg-info/PKG-INFO
src/collective.customlogin.egg-info/SOURCES.txt
src/collective.customlogin.egg-info/dependency_links.txt
src/collective.customlogin.egg-info/entry_points.txt
src/collective.customlogin.egg-info/namespace_packages.txt
src/collective.customlogin.egg-info/not-zip-safe
src/collective.customlogin.egg-info/requires.txt
src/collective.customlogin.egg-info/top_level.txt
src/collective/customlogin/__init__.py
src/collective/customlogin/configure.zcml
src/collective/customlogin/events.py
src/collective/customlogin/interfaces.py
src/collective/customlogin/plugin.py
src/collective/customlogin/redirect.py
src/collective/customlogin/testing.py
src/collective/customlogin/utils.py
src/collective/customlogin/tests/__init__.py
src/collective/customlogin/tests/robot_test.txt
src/collective/customlogin/tests/test_example.py
src/collective/customlogin/tests/test_robot.py
src/collective/customlogin/zmi/challenger.dtml