Metadata-Version: 1.1
Name: collective.customlogin
Version: 1.0.1
Summary: PAS Challenge plugin to allow custom login actions and redirects
Home-page: https://github.com/collective/collective.customlogin
Author: PretaGov
Author-email: software@pretaweb.com
License: gpl
Keywords: plone
Platform: UNKNOWN
Classifier: Environment :: Web Environment
Classifier: Framework :: Plone
Classifier: Operating System :: OS Independent
Classifier: Programming Language :: Python
Classifier: Programming Language :: Python :: 2.7
Classifier: Topic :: Software Development :: Libraries :: Python Modules
